memcached_udp.py
python_memcached_udp-0.2a0.dist-info/DESCRIPTION.rst
python_memcached_udp-0.2a0.dist-info/METADATA
python_memcached_udp-0.2a0.dist-info/RECORD
python_memcached_udp-0.2a0.dist-info/WHEEL
python_memcached_udp-0.2a0.dist-info/metadata.json
python_memcached_udp-0.2a0.dist-info/top_level.txt
