Metadata-Version: 2.0
Name: python-memcached-udp
Version: 0.2a0
Summary: A simple UDP Memcached client written in Python.
Home-page: https://github.com/idanmo/python-memcached-udp
Author: Idan Moyal
Author-email: idanmo@gmail.com
License: UNKNOWN
Keywords: memcached udp
Platform: UNKNOWN
Classifier: Development Status :: 3 - Alpha
Classifier: Intended Audience :: Developers
Classifier: Topic :: Software Development :: Libraries :: Python Modules
Classifier: License :: OSI Approved :: Apache Software License
Classifier: Programming Language :: Python :: 2.7
Classifier: Programming Language :: Python :: 3.4
Requires-Dist: six (==1.10.0)
